models/__init__.py
models/slim/__init__.py
models/slim/download_and_convert_data.py
models/slim/eval_image_classifier.py
models/slim/train_image_classifier.py
models/slim/datasets/__init__.py
models/slim/datasets/cifar10.py
models/slim/datasets/dataset_factory.py
models/slim/datasets/dataset_utils.py
models/slim/datasets/download_and_convert_cifar10.py
models/slim/datasets/download_and_convert_flowers.py
models/slim/datasets/download_and_convert_mnist.py
models/slim/datasets/flowers.py
models/slim/datasets/imagenet.py
models/slim/datasets/mnist.py
models/slim/deployment/__init__.py
models/slim/deployment/model_deploy.py
models/slim/deployment/model_deploy_test.py
models/slim/nets/__init__.py
models/slim/nets/alexnet.py
models/slim/nets/alexnet_test.py
models/slim/nets/cifarnet.py
models/slim/nets/inception.py
models/slim/nets/inception_resnet_v2.py
models/slim/nets/inception_resnet_v2_test.py
models/slim/nets/inception_utils.py
models/slim/nets/inception_v1.py
models/slim/nets/inception_v1_test.py
models/slim/nets/inception_v2.py
models/slim/nets/inception_v2_test.py
models/slim/nets/inception_v3.py
models/slim/nets/inception_v3_test.py
models/slim/nets/inception_v4.py
models/slim/nets/inception_v4_test.py
models/slim/nets/lenet.py
models/slim/nets/nets_factory.py
models/slim/nets/nets_factory_test.py
models/slim/nets/overfeat.py
models/slim/nets/overfeat_test.py
models/slim/nets/resnet_utils.py
models/slim/nets/resnet_v1.py
models/slim/nets/resnet_v1_test.py
models/slim/nets/resnet_v2.py
models/slim/nets/resnet_v2_test.py
models/slim/nets/vgg.py
models/slim/nets/vgg_test.py
models/slim/preprocessing/__init__.py
models/slim/preprocessing/cifarnet_preprocessing.py
models/slim/preprocessing/inception_preprocessing.py
models/slim/preprocessing/lenet_preprocessing.py
models/slim/preprocessing/preprocessing_factory.py
models/slim/preprocessing/vgg_preprocessing.py
transferflow/__init__.py
transferflow/utils.py
transferflow-0.1.8.dist-info/DESCRIPTION.rst
transferflow-0.1.8.dist-info/METADATA
transferflow-0.1.8.dist-info/RECORD
transferflow-0.1.8.dist-info/WHEEL
transferflow-0.1.8.dist-info/metadata.json
transferflow-0.1.8.dist-info/top_level.txt
