Metadata-Version: 2.0
Name: transferflow
Version: 0.1.8
Summary: Transfer learning for Tensorflow
Home-page: https://github.com/dominiek/transferflow
Author: UNKNOWN
Author-email: UNKNOWN
License: UNKNOWN
Platform: UNKNOWN
Requires-Dist: nnpack (>=0.1.0)
Requires-Dist: numpy (>=1.12.0)
Requires-Dist: opencv-python (>=3.2.0.6)
Requires-Dist: pytest (>=3.0.6)
Requires-Dist: scipy (>=0.18.1)
Requires-Dist: tensorflow (>=0.12.1)
